MANIFEST.in
README.md
setup.cfg
setup.py
UoL_Autograder.egg-info/PKG-INFO
UoL_Autograder.egg-info/SOURCES.txt
UoL_Autograder.egg-info/dependency_links.txt
UoL_Autograder.egg-info/entry_points.txt
UoL_Autograder.egg-info/requires.txt
UoL_Autograder.egg-info/top_level.txt
feedback/VERSION
feedback/__init__.py
feedback/__main__.py
feedback/signature.py
feedback/builder/__init__.py
feedback/builder/__main__.py
feedback/builder/run_autograder.sh
feedback/builder/setup.sh
feedback/cpp/__init__.py
feedback/cpp/compile_examiner.py
feedback/cpp/cpp_eval_util.cpp
feedback/cpp/cpp_eval_util.h
feedback/cpp/empty_main.cpp
feedback/cpp/json.hpp
feedback/cpp/ocache.py
feedback/general/__init__.py
feedback/general/config_tools.py
feedback/general/constants.py
feedback/general/execution.py
feedback/general/py_eval_util.py
feedback/general/result.py
feedback/general/util.py
feedback/general/validation.py
feedback/lookup/comment_feedback.json
feedback/lookup/cpp_compiler_feedback.json
feedback/lookup/cpp_eval_feedback.json
feedback/lookup/cpp_static_warnings.json
feedback/lookup/cpp_style_feedback.json
feedback/lookup/py_eval_feedback.json
feedback/lookup/py_runner_feedback.json
feedback/lookup/py_static_feedback.json
feedback/py/__init__.py