Metadata-Version: 1.1
Name: UoL-Autograder
Version: 0.8.4
Summary: General testing and feedback
Home-page: UNKNOWN
Author: Titusz Ban, Craig Evans & Sam Wilson @ Leeds Institute for Teaching Excellence
Author-email: el16ttb@leeds.ac.uk
License: ecl-2.0
Platform: UNKNOWN
Classifier: Development Status :: 4 - Beta
Classifier: Intended Audience :: Education
Classifier: Topic :: Software Development :: Build Tools
Classifier: License :: Free For Educational Use
Classifier: Programming Language :: Python :: 3
Classifier: Programming Language :: Python :: 3.4
Classifier: Programming Language :: Python :: 3.5
Classifier: Programming Language :: Python :: 3.6
Classifier: Programming Language :: Python :: 3.7
